README.txt
setup.cfg
setup.py
BeakerShowSessions.egg-info/PKG-INFO
BeakerShowSessions.egg-info/SOURCES.txt
BeakerShowSessions.egg-info/dependency_links.txt
BeakerShowSessions.egg-info/entry_points.txt
BeakerShowSessions.egg-info/namespace_packages.txt
BeakerShowSessions.egg-info/not-zip-safe
BeakerShowSessions.egg-info/requires.txt
BeakerShowSessions.egg-info/top_level.txt
beaker/__init__.py
beaker/scripts/__init__.py
beaker/scripts/sessions.py