Metadata-Version: 1.0
Name: BeakerShowSessions
Version: 0.1.3
Summary: A Beaker extension to show the active sessions
Home-page: UNKNOWN
Author: Linas Juskevicius
Author-email: linas@idiles.com
License: MIT
Keywords: beaker session database active
Platform: UNKNOWN
